rejocker/__init__.py
rejocker/rejocker.py
rejocker/resources/example.json
rejocker-0.5.dist-info/AUTHORS.md
rejocker-0.5.dist-info/LICENSE
rejocker-0.5.dist-info/METADATA
rejocker-0.5.dist-info/WHEEL
rejocker-0.5.dist-info/top_level.txt
rejocker-0.5.dist-info/RECORD
