Metadata-Version: 2.1
Name: rejocker
Version: 0.5
Summary: REst Json mOCK servER
Home-page: https://github.com/jctophefabre/rejocker
Author: Jean-Christophe Fabre
Author-email: jean-christophe.fabre@inrae.fr
License: GPLv3
Platform: UNKNOWN
Requires-Python: ~=3.5
Requires-Dist: flask
